server.py
sourcegraph_mcp-2.0.1.dist-info/licenses/LICENSE
sourcegraph_mcp-2.0.1.dist-info/METADATA
sourcegraph_mcp-2.0.1.dist-info/WHEEL
sourcegraph_mcp-2.0.1.dist-info/entry_points.txt
sourcegraph_mcp-2.0.1.dist-info/top_level.txt
sourcegraph_mcp-2.0.1.dist-info/RECORD
