Metadata-Version: 2.4
Name: sourcegraph-mcp
Version: 2.0.1
Summary: Model Context Protocol server for SourceGraph code search
Author: Dale Brubaker
License: MIT
Project-URL: Homepage, https://github.com/dalebrubaker/sourcegraph-mcp
Project-URL: Repository, https://github.com/dalebrubaker/sourcegraph-mcp
Project-URL: Issues, https://github.com/dalebrubaker/sourcegraph-mcp/issues
Project-URL: Documentation, https://github.com/dalebrubaker/sourcegraph-mcp#readme
Keywords: mcp,sourcegraph,code-search,claude,ai
Classifier: Development Status :: 4 - Beta
Classifier: Intended Audience :: Developers
Classifier: License :: OSI Approved :: MIT License
Classifier: Programming Language :: Python :: 3
Classifier: Programming Language :: Python :: 3.10
Classifier: Programming Language :: Python :: 3.11
Classifier: Programming Language :: Python :: 3.12
Classifier: Programming Language :: Python :: 3.13
Requires-Python: >=3.10
License-File: LICENSE
Requires-Dist: mcp>=1.0.0
Requires-Dist: httpx>=0.27.0
Dynamic: license-file
